zyjared_color/__init__.py
zyjared_color/base/__init__.py
zyjared_color/base/alias.py
zyjared_color/base/color.py
zyjared_color/base/color.pyi
zyjared_color/base/main.py
zyjared_color/base/styles.py
zyjared_color/base/utils.py
zyjared_color/base/zprint.py
zyjared_color/core/__init__.py
zyjared_color/core/method.py
zyjared_color/core/static.py
zyjared_color/core/style.py
zyjared_color/html/__init__.py
zyjared_color/html/alias.py
zyjared_color/html/html.py
zyjared_color/html/html.pyi
zyjared_color/html/static.py
zyjared_color/html/static.pyi
zyjared_color/html/styles.py
zyjared_color-0.5.9.dist-info/LICENSE
zyjared_color-0.5.9.dist-info/METADATA
zyjared_color-0.5.9.dist-info/WHEEL
zyjared_color-0.5.9.dist-info/RECORD
