Metadata-Version: 2.1
Name: zyjared-color
Version: 0.5.9
Summary: Personal font color utility library for Python
Author: zyjared
Author-email: zyjared@outlook.com
Requires-Python: >=3.12,<4.0
Classifier: Programming Language :: Python :: 3
Classifier: Programming Language :: Python :: 3.12
Classifier: Programming Language :: Python :: 3.13
Project-URL: documentation, https://github.com/zyjared/zyjared-color#readme
Project-URL: homepage, https://github.com/zyjared/zyjared-color
Project-URL: repository, https://github.com/zyjared/zyjared-color
